django_reverse_js/__init__.py
django_reverse_js/apps.py
django_reverse_js/conf.py
django_reverse_js/core.py
django_reverse_js/views.py
django_reverse_js/management/__init__.py
django_reverse_js/management/commands/__init__.py
django_reverse_js/management/commands/createstatic_reversejs.py
django_reverse_js/templates/django_reverse_js/url-resolver.js
django_reverse_js/templates/django_reverse_js/url-resolver.min.js
django_reverse_js/templates/django_reverse_js/url-resolver.tpl.js
django_reverse_js/templatetags/__init__.py
django_reverse_js/templatetags/reversejs.py
django_reverse_js-0.1.8.dist-info/licenses/LICENSE
django_reverse_js-0.1.8.dist-info/METADATA
django_reverse_js-0.1.8.dist-info/WHEEL
django_reverse_js-0.1.8.dist-info/top_level.txt
django_reverse_js-0.1.8.dist-info/RECORD
