Metadata-Version: 2.4
Name: django-reverse-js
Version: 0.1.8
Summary: Django URL handling in JavaScript
Author: Davide Setti
License-Expression: MIT
Project-URL: Homepage, https://github.com/sevdog/django-reverse-js
Project-URL: Bug Tracker, https://github.com/sevdog/django-reverse-js/issues
Classifier: Programming Language :: Python
Classifier: Programming Language :: Python :: 3
Classifier: Programming Language :: Python :: 3.10
Classifier: Programming Language :: Python :: 3.11
Classifier: Programming Language :: Python :: 3.12
Classifier: Programming Language :: Python :: 3.13
Classifier: Framework :: Django
Classifier: Framework :: Django :: 4.2
Classifier: Framework :: Django :: 5.0
Classifier: Framework :: Django :: 5.1
Classifier: Framework :: Django :: 5.2
Classifier: Operating System :: OS Independent
Classifier: Intended Audience :: Developers
Requires-Python: >=3.10
License-File: LICENSE
Requires-Dist: django>=4.2
Provides-Extra: tests
Requires-Dist: coverage[toml]; extra == "tests"
Requires-Dist: pytest; extra == "tests"
Requires-Dist: pytest-django; extra == "tests"
Requires-Dist: pytest-cov; extra == "tests"
Dynamic: license-file
